craftdl/__init__.py
craftdl/classification_net.py
craftdl/datasets.py
craftdl/exception.py
craftdl/linear_net.py
craftdl/nets.py
craftdl/plot.py
craftdl/util.py
craftdl-0.1.0.dist-info/METADATA
craftdl-0.1.0.dist-info/WHEEL
craftdl-0.1.0.dist-info/top_level.txt
craftdl-0.1.0.dist-info/RECORD
