Metadata-Version: 2.1
Name: craftdl
Version: 0.1.0
Summary: CraftDL is a library for quickly solving simple & common deep learning tasks
Home-page: https://github.com/uhasker/craftdl
Author: uhasker
Author-email: uhasker@protonmail.com
License: MIT
Requires-Dist: torch (==1.11.*)
Requires-Dist: matplotlib (==3.5.*)
Requires-Dist: tqdm (==4.64.*)
